LICENSE
MANIFEST.in
README.rst
distribute_setup.py
setup.py
bin/capture-api
janrain/__init__.py
janrain/utils.py
janrain/capture/__init__.py
janrain/capture/api.py
janrain/capture/cli.py
janrain/capture/config.py
janrain/capture/exceptions.py
janrain/capture/version.py
janrain/capture/test/__init__.py
janrain/capture/test/janrain-config
janrain/capture/test/test_api.py
janrain/capture/test/test_config.py
janrain/capture/test/test_errors.py
janrain_python_api.egg-info/PKG-INFO
janrain_python_api.egg-info/SOURCES.txt
janrain_python_api.egg-info/dependency_links.txt
janrain_python_api.egg-info/namespace_packages.txt
janrain_python_api.egg-info/requires.txt
janrain_python_api.egg-info/top_level.txt