Metadata-Version: 1.1
Name: janrain-python-api
Version: 0.4.0
Summary: Python interface to the Janrain Capture API.
Home-page: http://developers.janrain.com/
Author: Micah Carrick
Author-email: micah@janrain.com
License: UNKNOWN
Platform: UNKNOWN
Classifier: Development Status :: 5 - Production/Stable
Classifier: Environment :: Console
Classifier: Intended Audience :: Developers
Classifier: Operating System :: OS Independent
Classifier: Programming Language :: Python
Classifier: Topic :: Software Development :: Libraries :: Python Modules
Classifier: Topic :: Internet :: WWW/HTTP
Classifier: License :: OSI Approved :: MIT License
